bota_driver/__init__.py
bota_driver/bota_driver_ext.cpython-39-x86_64-linux-gnu.so
bota_driver/cpp_lib/lib/libBotaDriver.so
bota_driver-1.1.5.dist-info/METADATA
bota_driver-1.1.5.dist-info/WHEEL
bota_driver-1.1.5.dist-info/RECORD
