Metadata-Version: 2.1
Name: bota-driver
Version: 1.1.5
Summary: Python binding for the Bota Driver C++ library
Author-Email: Raul Cruz-Oliver <support@botasys.com>
Classifier: License :: OSI Approved :: BSD License
Project-URL: Homepage, https://botasys.com
Requires-Python: >=3.8
